Pandas2Shp.py
Pandas2Shp-0.0.2.dist-info/LICENSE
Pandas2Shp-0.0.2.dist-info/METADATA
Pandas2Shp-0.0.2.dist-info/WHEEL
Pandas2Shp-0.0.2.dist-info/top_level.txt
Pandas2Shp-0.0.2.dist-info/RECORD
