Metadata-Version: 2.1
Name: Pandas2Shp
Version: 0.0.2
Summary: Create shp file for geo-spatial analysis from longitude and latitude
Home-page: https://github.com/StatguyUser/Pandas2Shp
Author: StatguyUser
License: UNKNOWN
Download-URL: https://github.com/StatguyUser/Pandas2Shp.git
Platform: UNKNOWN
Requires-Dist: geopandas
Requires-Dist: pandas
